CHANGELOG.md
LICENSE
MANIFEST.in
README.md
mynotes.txt
setup.cfg
setup.py
tox.ini
Mopiqtt.egg-info/PKG-INFO
Mopiqtt.egg-info/SOURCES.txt
Mopiqtt.egg-info/dependency_links.txt
Mopiqtt.egg-info/entry_points.txt
Mopiqtt.egg-info/not-zip-safe
Mopiqtt.egg-info/requires.txt
Mopiqtt.egg-info/top_level.txt
mopiqtt/__init__.py
mopiqtt/ext.conf
mopiqtt/frontend.py
mopiqtt/mqtt.py
mopiqtt/utils.py
tests/__init__.py
tests/conftest.py
tests/test_smoke.py