Metadata-Version: 2.1
Name: Mopiqtt
Version: 1.0.9
Summary: Control mopidy music server through MQTT broker
Home-page: https://github.com/fmarzocca/mopiqtt
Author: Fabio Marzocca
Author-email: marzoccafabio@gmail.com
License: Apache License, Version 2.0
Platform: UNKNOWN
Classifier: Development Status :: 5 - Production/Stable
Classifier: Intended Audience :: End Users/Desktop
Classifier: License :: OSI Approved :: Apache Software License
Classifier: Operating System :: OS Independent
Classifier: Programming Language :: Python
Classifier: Programming Language :: Python :: 3
Classifier: Programming Language :: Python :: 3.7
Classifier: Topic :: Multimedia :: Sound/Audio :: Players
Classifier: Environment :: No Input/Output (Daemon)
